vulcan/__init__.py
vulcan/foundry/__init__.py
vulcan/foundry/torch_composer.py
vulcanx-0.1.0.dist-info/licenses/LICENSE
vulcanx-0.1.0.dist-info/METADATA
vulcanx-0.1.0.dist-info/WHEEL
vulcanx-0.1.0.dist-info/top_level.txt
vulcanx-0.1.0.dist-info/RECORD
